fib_0112/__init__.py
fib_0112/fib.py
fib_0112-0.0.1.dist-info/LICENSE
fib_0112-0.0.1.dist-info/METADATA
fib_0112-0.0.1.dist-info/WHEEL
fib_0112-0.0.1.dist-info/top_level.txt
fib_0112-0.0.1.dist-info/RECORD
