Metadata-Version: 2.1
Name: fib-0112
Version: 0.0.1
Summary: fibonacci sequence
Author: sabaOAK
Author-email: ratianisaba@gmail.com
Classifier: Programming Language :: Python :: 3
Classifier: License :: OSI Approved :: MIT License
Classifier: Operating System :: OS Independent
Requires-Python: >=3.6
License-File: LICENSE
